{
  "$schema": "https://ui.shadcn.com/schema/registry-item.json",
  "name": "icon-button",
  "type": "registry:component",
  "title": "IconButton",
  "description": "アイコンボタンはフォームの送信、ダイアログの展開、アクションのキャンセル、削除の実行など、アクションやイベントのトリガーとして使用するコンポーネントです。",
  "files": [
    {
      "path": "src/components/ui/icon-button/index.tsx",
      "type": "registry:component"
    }
  ],
  "dependencies": ["radix-ui"],
  "registryDependencies": [
    "https://sparkle-design.goodpatch.com/r/icon.json",
    "https://sparkle-design.goodpatch.com/r/spinner.json"
  ]
}
